tuxpub/__init__.py
tuxpub/config.py
tuxpub/filters.py
tuxpub/resources.py
tuxpub/static/robots.txt
tuxpub/static/styles.css
tuxpub/templates/404.html
tuxpub/templates/files.html
tuxpub/templates/footer.html
tuxpub/templates/layout.html
tuxpub/templates/root.html
tuxpub-0.1.11.dist-info/LICENSE
tuxpub-0.1.11.dist-info/METADATA
tuxpub-0.1.11.dist-info/WHEEL
tuxpub-0.1.11.dist-info/top_level.txt
tuxpub-0.1.11.dist-info/RECORD
