Metadata-Version: 2.1
Name: tuxpub
Version: 0.1.11
Summary: The Serverless File Server
Home-page: https://gitlab.com/Linaro/tuxpub
Author: Linaro Limited
License: UNKNOWN
Platform: UNKNOWN
Classifier: Development Status :: 3 - Alpha
Classifier: Environment :: Web Environment
Classifier: Framework :: Flask
Classifier: Intended Audience :: Developers
Classifier: Programming Language :: Python :: 3
Classifier: License :: OSI Approved :: MIT License
Classifier: Operating System :: OS Independent
Classifier: Topic :: Software Development :: Testing
Classifier: Topic :: System :: Operating System Kernels :: Linux
License-File: LICENSE
Requires-Dist: arrow
Requires-Dist: boto3
Requires-Dist: Flask
Requires-Dist: Flask-Bootstrap
Requires-Dist: Jinja2
Requires-Dist: hurry.filesize
